README.rst
setup.py
p0f/__init__.py
p0f/logparser.py
p0f.egg-info/PKG-INFO
p0f.egg-info/SOURCES.txt
p0f.egg-info/dependency_links.txt
p0f.egg-info/top_level.txt