Metadata-Version: 1.1
Name: p0f
Version: 0.1.1
Summary: API client for p0f3
Home-page: https://github.com/ojarva/p0f3-api-py
Author: Olli Jarva
Author-email: olli@jarva.fi
License: MIT
Download-URL: https://github.com/ojarva/p0f3-api-py
Keywords: p0f fingerprinting API client
Platform: UNKNOWN
Classifier: Development Status :: 3 - Alpha
Classifier: Topic :: Software Development :: Libraries
Classifier: License :: OSI Approved :: MIT License
